versionedobj/__init__.py
versionedobj/exceptions.py
versionedobj/object.py
versionedobj/serializer.py
versionedobj/types.py
versionedobj/utils.py
versionedobj-2.0.4.dist-info/LICENSE
versionedobj-2.0.4.dist-info/METADATA
versionedobj-2.0.4.dist-info/WHEEL
versionedobj-2.0.4.dist-info/top_level.txt
versionedobj-2.0.4.dist-info/RECORD
