Metadata-Version: 2.1
Name: versionedobj
Version: 2.0.4
Summary: Easy object serialization & versioning framework
Home-page: http://github.com/eriknyquist/versionedobj
Author: Erik Nyquist
Author-email: eknyquist@gmail.com
License: Apache 2.0
Project-URL: Documentation, https://eriknyquist.github.io/versionedobj
Project-URL: Issues, https://github.com/eriknyquist/versionedobj/issues
Project-URL: Contributions, https://eriknyquist.github.io/versionedobj/#contributions
Keywords: serialization,json,api,marshal,marshalling,deserialization,validation,schema
Classifier: Development Status :: 5 - Production/Stable
Classifier: Intended Audience :: Developers
Classifier: Intended Audience :: Science/Research
Classifier: Intended Audience :: Education
Classifier: Intended Audience :: Information Technology
Classifier: License :: OSI Approved :: Apache Software License
Classifier: Programming Language :: Python :: 3
Classifier: Programming Language :: Python :: 3.7
Classifier: Programming Language :: Python :: 3.8
Classifier: Programming Language :: Python :: 3.9
Classifier: Programming Language :: Python :: 3.10
Requires-Python: >=3.7
License-File: LICENSE
